spongebob/__init__.py
spongebob/banner.txt
spongebob/spongebob.jpg
spongebob/spongebob.py
spongebob-0.1.3.dist-info/LICENSE
spongebob-0.1.3.dist-info/METADATA
spongebob-0.1.3.dist-info/WHEEL
spongebob-0.1.3.dist-info/top_level.txt
spongebob-0.1.3.dist-info/RECORD
