Metadata-Version: 2.1
Name: spongebob
Version: 0.1.3
Summary: DeSCriPTiOn (OpTiONaL)
Home-page: https://github.com/ltskinner/spongebob
Author: ltskinner
Author-email: UNKNOWN
License: MIT
Platform: UNKNOWN
Requires-Dist: docx2txt
Requires-Dist: python-docx
